flask_static_compress/__about__.py
flask_static_compress/__init__.py
Flask_Static_Compress-1.0.3.dist-info/AUTHORS
Flask_Static_Compress-1.0.3.dist-info/LICENSE
Flask_Static_Compress-1.0.3.dist-info/METADATA
Flask_Static_Compress-1.0.3.dist-info/WHEEL
Flask_Static_Compress-1.0.3.dist-info/top_level.txt
Flask_Static_Compress-1.0.3.dist-info/RECORD
